openimis_be_social_protection-1.4.0.dist-info/licenses/LICENSE.md
social_protection/__init__.py
social_protection/admin.py
social_protection/apps.py
social_protection/custom_filters.py
social_protection/data_masking.py
social_protection/documents.py
social_protection/export_mixin.py
social_protection/gql_mutations.py
social_protection/gql_queries.py
social_protection/models.py
social_protection/schema.py
social_protection/services.py
social_protection/urls.py
social_protection/utils.py
social_protection/validation.py
social_protection/views.py
social_protection/management/__init__.py
social_protection/management/commands/__init__.py
social_protection/management/commands/add_beneficiary_data_to_opensearch.py
social_protection/migrations/0001_initial.py
social_protection/migrations/0002_add_benefit_plan_rights_to_admin.py
social_protection/migrations/0003_beneficiary_historicalbeneficiary.py
social_protection/migrations/0004_add_beneficiary_rights_to_admin.py
social_protection/migrations/0005_auto_20230607_0759.py
social_protection/migrations/0006_add_description_to_benefit_plan.py
social_protection/migrations/0007_auto_20230622_1015.py
social_protection/migrations/0008_benefitplandatauploadrecords_historicalbenefitplandatauploadrecords.py
social_protection/migrations/0009_add_schema_admin_and_schema_roles.py
social_protection/migrations/0010_auto_20230803_1735.py
social_protection/migrations/0011_alter_beneficiary_date_created_and_more.py
social_protection/migrations/0012_benefitplanmutation.py
social_protection/migrations/0013_alter_benefitplan_max_beneficiaries_and_more.py
social_protection/migrations/0014_replace_benefitplan_max_beneficiaries_values.py
social_protection/migrations/0015_historicalactivity_activity.py
social_protection/migrations/0016_project_historicalproject.py
social_protection/migrations/0017_add_activity_project_rights_to_admin.py
social_protection/migrations/0018_alter_historicalproject_status_alter_project_status.py
social_protection/migrations/0019_project_status_update.py
openimis_be_social_protection-1.4.0.dist-info/METADATA
openimis_be_social_protection-1.4.0.dist-info/WHEEL
openimis_be_social_protection-1.4.0.dist-info/top_level.txt
openimis_be_social_protection-1.4.0.dist-info/RECORD
